{
  "description": "FailureDomain represents the different configurations required to spread Machines across failure domains on different platforms.",
  "type": "object",
  "required": [
    "platform"
  ],
  "properties": {
    "aws": {
      "description": "AWS configures failure domain information for the AWS platform.",
      "type": [
        "array",
        "null"
      ],
      "items": {
        "description": "AWSFailureDomain configures failure domain information for the AWS platform.",
        "type": [
          "object",
          "null"
        ],
        "properties": {
          "placement": {
            "description": "AWSFailureDomainPlacement configures the placement information for the AWSFailureDomain.",
            "type": [
              "object",
              "null"
            ],
            "required": [
              "availabilityZone"
            ],
            "properties": {
              "availabilityZone": {
                "description": "AvailabilityZone is the availability zone of the instance.",
                "type": "string",
                "default": ""
              }
            },
            "additionalProperties": false
          },
          "subnet": {
            "description": "AWSResourceReference is a reference to a specific AWS resource by ID, ARN, or filters. Only one of ID, ARN or Filters may be specified. Specifying more than one will result in a validation error.",
            "type": [
              "object",
              "null"
            ],
            "required": [
              "type"
            ],
            "properties": {
              "arn": {
                "description": "ARN of resource.",
                "type": [
                  "string",
                  "null"
                ]
              },
              "filters": {
                "description": "Filters is a set of filters used to identify a resource.",
                "type": [
                  "array",
                  "null"
                ],
                "items": {
                  "description": "AWSResourceFilter is a filter used to identify an AWS resource",
                  "type": [
                    "object",
                    "null"
                  ],
                  "required": [
                    "name"
                  ],
                  "properties": {
                    "name": {
                      "description": "Name of the filter. Filter names are case-sensitive.",
                      "type": "string",
                      "default": ""
                    },
                    "values": {
                      "description": "Values includes one or more filter values. Filter values are case-sensitive.",
                      "type": [
                        "array",
                        "null"
                      ],
                      "items": {
                        "type": [
                          "string",
                          "null"
                        ],
                        "default": ""
                      }
                    }
                  },
                  "additionalProperties": false
                }
              },
              "id": {
                "description": "ID of resource.",
                "type": [
                  "string",
                  "null"
                ]
              },
              "type": {
                "description": "Type determines how the reference will fetch the AWS resource.",
                "type": "string",
                "default": ""
              }
            },
            "x-kubernetes-unions": [
              {
                "discriminator": "type",
                "fields-to-discriminateBy": {
                  "arn": "ARN",
                  "filters": "Filters",
                  "id": "ID"
                }
              }
            ],
            "additionalProperties": false
          }
        },
        "additionalProperties": false
      }
    },
    "azure": {
      "description": "Azure configures failure domain information for the Azure platform.",
      "type": [
        "array",
        "null"
      ],
      "items": {
        "description": "AzureFailureDomain configures failure domain information for the Azure platform.",
        "type": [
          "object",
          "null"
        ],
        "required": [
          "zone"
        ],
        "properties": {
          "zone": {
            "description": "Availability Zone for the virtual machine. If nil, the virtual machine should be deployed to no zone.",
            "type": "string",
            "default": ""
          }
        },
        "additionalProperties": false
      }
    },
    "gcp": {
      "description": "GCP configures failure domain information for the GCP platform.",
      "type": [
        "array",
        "null"
      ],
      "items": {
        "description": "GCPFailureDomain configures failure domain information for the GCP platform",
        "type": [
          "object",
          "null"
        ],
        "required": [
          "zone"
        ],
        "properties": {
          "zone": {
            "description": "Zone is the zone in which the GCP machine provider will create the VM.",
            "type": "string",
            "default": ""
          }
        },
        "additionalProperties": false
      }
    },
    "platform": {
      "description": "Platform identifies the platform for which the FailureDomain represents. Currently supported values are AWS, Azure, and GCP.",
      "type": [
        "string",
        "null"
      ],
      "default": ""
    }
  },
  "x-kubernetes-unions": [
    {
      "discriminator": "platform",
      "fields-to-discriminateBy": {
        "aws": "AWS",
        "azure": "Azure",
        "gcp": "GCP"
      }
    }
  ],
  "additionalProperties": false,
  "$schema": "http://json-schema.org/schema#"
}